torch_contrastive_framework/__init__.py
torch_contrastive_framework/train.py
torch_contrastive_framework-0.1.0.dist-info/LICENSE
torch_contrastive_framework-0.1.0.dist-info/METADATA
torch_contrastive_framework-0.1.0.dist-info/WHEEL
torch_contrastive_framework-0.1.0.dist-info/top_level.txt
torch_contrastive_framework-0.1.0.dist-info/RECORD
